{    
  "level": 9,
  "fuel" : 180,
  "oxygen" : 300,

  "camera center":
  {
    "x": 0,
    "y": 0
  },

  "camera size":
  {
    "x": 2500,
    "y": 1265.625
  },

  "exit":
  {
    "x": 1100,
    "y": 0    
  },
  
  "entrance":
  {
    "x": 0,
    "y": 0
  },

  "pressure sources":
  [
    {"origin": {"x": 550,"y": -168.75}, "strength":-1050, "radius":350},
    {"origin": {"x": -550,"y": -168.75}, "strength":-1050, "radius":350}
  ],

    "shockboxes":
  [
    {"x": 550, "y": -168.75},
    {"x": -550, "y": -168.75},

    {"x": -1100, "y": -500},
    {"x": -900, "y": -175},
    {"x": -800, "y": 175},
    {"x": -700, "y": 500},

    {"x": -550, "y": -337.5},
    
    {"x": 0, "y": -500},

    {"x": -200, "y": -175},
    {"x": -200, "y": 175},
    {"x": -200, "y": 500},

    {"x": 1100, "y": -500},
    {"x": 900, "y": -175},
    {"x": 800, "y": 175},
    {"x": 700, "y": 500},

    {"x": 550, "y": -337.5},
    
    {"x": 200, "y": -175},
    {"x": 200, "y": 175},
    {"x": 200, "y": 500}



  ],

  "walls":
  [
    {"origin": {"x": -1250, "y": -632}, "endpoint": {"x": 1250, "y": -632}, "radius": 40},
    {"origin": {"x": -1250,"y": 632},"endpoint": {"x": 1250,"y": 632},"radius": 40},

    {"origin": {"x": -1250,"y": 632},"endpoint": {"x": -1250,"y": -632},"radius": 40},
    {"origin": {"x": 1250,"y": -632},"endpoint": {"x": 1250,"y": 632},"radius": 40},

    {"origin": {"x": -150,"y": 250},"endpoint": {"x": 0,"y": 200},"radius": 40, "lethal": true},
    {"origin": {"x": 150,"y": 250},"endpoint": {"x": 0,"y": 200},"radius": 40, "lethal": true},

    {"origin": {"x": -530,"y": 40},"endpoint": {"x": -530,"y": 60},"radius": 20},
    {"origin": {"x": -530,"y": 200},"endpoint": {"x": -530,"y": 220},"radius": 20},
    {"origin": {"x": -530,"y": 400},"endpoint": {"x": -530,"y": 420},"radius": 20},
    
    {"origin": {"x": 530,"y": 40},"endpoint": {"x": 530,"y": 60},"radius": 20},
    {"origin": {"x": 530,"y": 200},"endpoint": {"x": 530,"y": 220},"radius": 20},
    {"origin": {"x": 530,"y": 400},"endpoint": {"x": 530,"y": 420},"radius": 20}


  ],

    "fans":
  [
    {"origin": {"x": 1220,"y": -337.5,"strength": 150},"endpoint": {"x": 0,"y": -337.5,"strength": 50},"width": 150},
    {"origin": {"x": 1220,"y": -500,"strength": 250},"endpoint": {"x": -100,"y": -500,"strength": 50},"width": 150},
    {"origin": {"x": -1220,"y": 520,"strength": 450},"endpoint": {"x": 1200,"y": 520,"strength": 100},"width": 150},
    {"origin": {"x": -1100,"y": 610,"strength": 50},"endpoint": {"x": -1100,"y": 500,"strength": 50},"width": 150}
  ]
}


